[
  {
    "id": 1,
    "name": "Miso",
    "description": "Ramen, lotus root, daikon, radish, shiitake, garlic...",
    "image": "https://example.com/images/miso_soup.png",
    "price": 4,
    "category": "Soup",
    "type": "Veggie"
  },
  {
    "id": 2,
    "name": "Chicken noodle",
    "description": "Ramen, pumpkin, greens, nori, tomatoes, chili...",
    "image": "https://example.com/images/chicken_noodle.png",
    "price": 5,
    "category": "Soup",
    "type": "Poultry"
  },
  {
    "id": 3,
    "name": "Spicy",
    "description": "Ramen, vegetable broth, basil, paprika, carrot...",
    "image": "https://example.com/images/spicy_ramen.png",
    "price": 5,
    "category": "Soup",
    "type": "Veggie"
  },
  {
    "id": 4,
    "name": "Tonkatsu",
    "description": "Ramen, vegetable broth, bean sprouts, carrots...",
    "image": "https://example.com/images/tonkatsu.png",
    "price": 4,
    "category": "Soup",
    "type": "Meat"
  }
]